<?xml version="1.0" encoding="UTF-8"?>
<fb version="0.4.0" size="5439">
  <f>
    <added t="I">8</added>
    <cycles t="I">5</cycles>
    <error>
      <v t="S">GET https://api.github.com/users/objectionary/repos?per_page=100: 403 - API rate limit exceeded for site ID installation. If you reach out to GitHub Support for help, please include the request ID 3410:3BC8F5:21DC65EA:221C7071:66E655D0 and timestamp 2024-09-15 03:34:40 UTC. // See: https://docs.github.com/rest/overview/rate-limits-for-the-rest-api</v>
      <v t="S">GET https://api.github.com/users/objectionary/repos?per_page=100: 403 - API rate limit exceeded for site ID installation. If you reach out to GitHub Support for help, please include the request ID 3410:3BC8F5:21DD36A4:221D42F7:66E6560E and timestamp 2024-09-15 03:35:42 UTC. // See: https://docs.github.com/rest/overview/rate-limits-for-the-rest-api</v>
      <v t="S">GET https://api.github.com/users/objectionary/repos?per_page=100: 403 - API rate limit exceeded for site ID installation. If you reach out to GitHub Support for help, please include the request ID 3410:3BC8F5:21DE0185:221E0FCE:66E6564B and timestamp 2024-09-15 03:36:43 UTC. // See: https://docs.github.com/rest/overview/rate-limits-for-the-rest-api</v>
      <v t="S">GET https://api.github.com/users/objectionary/repos?per_page=100: 403 - API rate limit exceeded for site ID installation. If you reach out to GitHub Support for help, please include the request ID 3410:3BC8F5:21DECB18:221EDB40:66E65687 and timestamp 2024-09-15 03:37:43 UTC. // See: https://docs.github.com/rest/overview/rate-limits-for-the-rest-api</v>
      <v t="S">GET https://api.github.com/users/objectionary/repos?per_page=100: 403 - API rate limit exceeded for site ID installation. If you reach out to GitHub Support for help, please include the request ID 3410:3BC8F5:21DF9D96:221FAF84:66E656C4 and timestamp 2024-09-15 03:38:44 UTC. // See: https://docs.github.com/rest/overview/rate-limits-for-the-rest-api</v>
      <v t="S">GET https://api.github.com/users/objectionary/repos?per_page=100: 403 - API rate limit exceeded for site ID installation. If you reach out to GitHub Support for help, please include the request ID 3410:3BC8F5:21E05DE2:222071B1:66E65701 and timestamp 2024-09-15 03:39:46 UTC. // See: https://docs.github.com/rest/overview/rate-limits-for-the-rest-api</v>
      <v t="S">GET https://api.github.com/users/objectionary/repos?per_page=100: 403 - API rate limit exceeded for site ID installation. If you reach out to GitHub Support for help, please include the request ID 3410:3BC8F5:21E17D7B:22219364:66E6573E and timestamp 2024-09-15 03:40:46 UTC. // See: https://docs.github.com/rest/overview/rate-limits-for-the-rest-api</v>
      <v t="S">GET https://api.github.com/users/objectionary/repos?per_page=100: 403 - API rate limit exceeded for site ID installation. If you reach out to GitHub Support for help, please include the request ID 3410:3BC8F5:21E2FF55:22231722:66E6577B and timestamp 2024-09-15 03:41:47 UTC. // See: https://docs.github.com/rest/overview/rate-limits-for-the-rest-api</v>
      <v t="S">GET https://api.github.com/users/objectionary/repos?per_page=100: 403 - API rate limit exceeded for site ID installation. If you reach out to GitHub Support for help, please include the request ID 3410:3BC8F5:21E42A73:222443CA:66E657B8 and timestamp 2024-09-15 03:42:48 UTC. // See: https://docs.github.com/rest/overview/rate-limits-for-the-rest-api</v>
      <v t="S">GET https://api.github.com/users/objectionary/repos?per_page=100: 403 - API rate limit exceeded for site ID installation. If you reach out to GitHub Support for help, please include the request ID 3410:3BC8F5:21E4E26B:2224FD9A:66E657F5 and timestamp 2024-09-15 03:43:49 UTC. // See: https://docs.github.com/rest/overview/rate-limits-for-the-rest-api</v>
      <v t="S">GET https://api.github.com/users/objectionary/repos?per_page=100: 403 - API rate limit exceeded for site ID installation. If you reach out to GitHub Support for help, please include the request ID 3410:3BC8F5:21E5C757:2225E472:66E65832 and timestamp 2024-09-15 03:44:50 UTC. // See: https://docs.github.com/rest/overview/rate-limits-for-the-rest-api</v>
      <v t="S">GET https://api.github.com/users/objectionary/repos?per_page=100: 403 - API rate limit exceeded for site ID installation. If you reach out to GitHub Support for help, please include the request ID 3410:3BC8F5:21E68A2A:2226A943:66E6586F and timestamp 2024-09-15 03:45:51 UTC. // See: https://docs.github.com/rest/overview/rate-limits-for-the-rest-api</v>
      <v t="S">GET https://api.github.com/users/objectionary/repos?per_page=100: 403 - API rate limit exceeded for site ID installation. If you reach out to GitHub Support for help, please include the request ID 3410:3BC8F5:21E75168:2227724F:66E658AC and timestamp 2024-09-15 03:46:52 UTC. // See: https://docs.github.com/rest/overview/rate-limits-for-the-rest-api</v>
    </error>
    <removed t="I">8</removed>
    <seconds t="F">792.638521359</seconds>
    <version t="S">0.26.1</version>
    <what t="S">judges-summary</what>
    <when t="T">2024-09-15T03:46:52Z</when>
  </f>
  <f>
    <_id t="I">1</_id>
    <_time t="T">2024-09-15T03:33:39Z</_time>
    <_version t="S">0.4.0/0.26.1/</_version>
    <what t="S">dimensions-of-terrain</what>
    <when t="T">2024-09-15T03:33:39Z</when>
  </f>
  <f>
    <_id t="I">2</_id>
    <_time t="T">2024-09-15T03:36:43Z</_time>
    <_version t="S">0.4.0/0.26.1/</_version>
    <since t="T">2024-08-18T03:36:43Z</since>
    <what t="S">quality-of-service</what>
    <when t="T">2024-09-15T03:36:43Z</when>
  </f>
  <f>
    <_id t="I">3</_id>
    <_time t="T">2024-09-15T03:37:44Z</_time>
    <_version t="S">0.4.0/0.26.1/</_version>
    <since t="T">2024-08-18T03:37:44Z</since>
    <what t="S">quantity-of-deliverables</what>
    <when t="T">2024-09-15T03:37:44Z</when>
  </f>
</fb>
