<?xml version="1.0" encoding="UTF-8"?>
<fb version="0.4.0" size="5403">
  <f>
    <added t="I">8</added>
    <cycles t="I">5</cycles>
    <error>
      <v t="S">GET https://api.github.com/users/objectionary/repos?per_page=100: 403 - API rate limit exceeded for site ID installation. If you reach out to GitHub Support for help, please include the request ID 0C70:183C:14C2C3F:2757FEC:66CD7FE8 and timestamp 2024-08-27 07:27:36 UTC. // See: https://docs.github.com/rest/overview/rate-limits-for-the-rest-api</v>
      <v t="S">GET https://api.github.com/users/objectionary/repos?per_page=100: 403 - API rate limit exceeded for site ID installation. If you reach out to GitHub Support for help, please include the request ID 0C70:14E98B:1DB1A5A:3884FAF:66CD8025 and timestamp 2024-08-27 07:28:37 UTC. // See: https://docs.github.com/rest/overview/rate-limits-for-the-rest-api</v>
      <v t="S">GET https://api.github.com/users/objectionary/repos?per_page=100: 403 - API rate limit exceeded for site ID installation. If you reach out to GitHub Support for help, please include the request ID 0C70:14E98B:1DBCA5C:389A9F5:66CD8061 and timestamp 2024-08-27 07:29:37 UTC. // See: https://docs.github.com/rest/overview/rate-limits-for-the-rest-api</v>
      <v t="S">GET https://api.github.com/users/objectionary/repos?per_page=100: 403 - API rate limit exceeded for site ID installation. If you reach out to GitHub Support for help, please include the request ID 0C70:71CE2:1A3B034:31D332A:66CD809D and timestamp 2024-08-27 07:30:38 UTC. // See: https://docs.github.com/rest/overview/rate-limits-for-the-rest-api</v>
      <v t="S">GET https://api.github.com/users/objectionary/repos?per_page=100: 403 - API rate limit exceeded for site ID installation. If you reach out to GitHub Support for help, please include the request ID 0C70:183C:14F3376:27B707F:66CD80DA and timestamp 2024-08-27 07:31:38 UTC. // See: https://docs.github.com/rest/overview/rate-limits-for-the-rest-api</v>
      <v t="S">GET https://api.github.com/users/objectionary/repos?per_page=100: 403 - API rate limit exceeded for site ID installation. If you reach out to GitHub Support for help, please include the request ID 0C70:71CE2:1A546FC:320548D:66CD8116 and timestamp 2024-08-27 07:32:38 UTC. // See: https://docs.github.com/rest/overview/rate-limits-for-the-rest-api</v>
      <v t="S">GET https://api.github.com/users/objectionary/repos?per_page=100: 403 - API rate limit exceeded for site ID installation. If you reach out to GitHub Support for help, please include the request ID 0C70:183C:150A666:27E4775:66CD8153 and timestamp 2024-08-27 07:33:39 UTC. // See: https://docs.github.com/rest/overview/rate-limits-for-the-rest-api</v>
      <v t="S">GET https://api.github.com/users/objectionary/repos?per_page=100: 403 - API rate limit exceeded for site ID installation. If you reach out to GitHub Support for help, please include the request ID 0C70:71CE2:1A6CC59:32353D8:66CD818F and timestamp 2024-08-27 07:34:39 UTC. // See: https://docs.github.com/rest/overview/rate-limits-for-the-rest-api</v>
      <v t="S">GET https://api.github.com/users/objectionary/repos?per_page=100: 403 - API rate limit exceeded for site ID installation. If you reach out to GitHub Support for help, please include the request ID 0C70:71CE2:1A787CD:324C665:66CD81CC and timestamp 2024-08-27 07:35:40 UTC. // See: https://docs.github.com/rest/overview/rate-limits-for-the-rest-api</v>
      <v t="S">GET https://api.github.com/users/objectionary/repos?per_page=100: 403 - API rate limit exceeded for site ID installation. If you reach out to GitHub Support for help, please include the request ID 0C70:183C:152F7B5:282D2E0:66CD8208 and timestamp 2024-08-27 07:36:40 UTC. // See: https://docs.github.com/rest/overview/rate-limits-for-the-rest-api</v>
      <v t="S">GET https://api.github.com/users/objectionary/repos?per_page=100: 403 - API rate limit exceeded for site ID installation. If you reach out to GitHub Support for help, please include the request ID 0C70:14E98B:1E1A1DB:3952A01:66CD8244 and timestamp 2024-08-27 07:37:41 UTC. // See: https://docs.github.com/rest/overview/rate-limits-for-the-rest-api</v>
      <v t="S">GET https://api.github.com/users/objectionary/repos?per_page=100: 403 - API rate limit exceeded for site ID installation. If you reach out to GitHub Support for help, please include the request ID 0C70:183C:1549065:285F524:66CD8281 and timestamp 2024-08-27 07:38:41 UTC. // See: https://docs.github.com/rest/overview/rate-limits-for-the-rest-api</v>
      <v t="S">GET https://api.github.com/users/objectionary/repos?per_page=100: 403 - API rate limit exceeded for site ID installation. If you reach out to GitHub Support for help, please include the request ID 0C70:14E98B:1E31055:397FB1A:66CD82BD and timestamp 2024-08-27 07:39:41 UTC. // See: https://docs.github.com/rest/overview/rate-limits-for-the-rest-api</v>
    </error>
    <removed t="I">8</removed>
    <seconds t="F">786.875761248</seconds>
    <version t="S">0.26.0</version>
    <what t="S">judges-summary</what>
    <when t="T">2024-08-27T07:39:41Z</when>
  </f>
  <f>
    <_id t="I">1</_id>
    <_time t="T">2024-08-27T07:26:35Z</_time>
    <_version t="S">0.4.0/0.26.0/</_version>
    <what t="S">dimensions-of-terrain</what>
    <when t="T">2024-08-27T07:26:35Z</when>
  </f>
  <f>
    <_id t="I">2</_id>
    <_time t="T">2024-08-27T07:29:37Z</_time>
    <_version t="S">0.4.0/0.26.0/</_version>
    <since t="T">2024-07-30T07:29:37Z</since>
    <what t="S">quality-of-service</what>
    <when t="T">2024-08-27T07:29:37Z</when>
  </f>
  <f>
    <_id t="I">3</_id>
    <_time t="T">2024-08-27T07:30:38Z</_time>
    <_version t="S">0.4.0/0.26.0/</_version>
    <since t="T">2024-07-30T07:30:38Z</since>
    <what t="S">quantity-of-deliverables</what>
    <when t="T">2024-08-27T07:30:38Z</when>
  </f>
</fb>
